<?xml version="1.0" encoding="UTF-8"?>
<metadata>
	<idinfo>
		<citation>
			<citeinfo>
				<origin>Environmental Systems Research Institute (Redlands, Calif.)</origin>
				<pubdate>1996</pubdate>
				<title>World Mountain Peaks, 1996</title>
				<geoform>vector digital data</geoform>
				<serinfo>
					<sername>ArcAtlas</sername>
				</serinfo>
				<pubinfo>
					<pubplace>Redlands, Calif.</pubplace>
					<publish>Environmental Systems Research Institute (Redlands, Calif.)</publish>
				</pubinfo>
				<onlink>https://www1.columbia.edu/sec/acis/eds/dgate/studies/C1301/data/esri_1996_world_peaks.zip</onlink>
			</citeinfo>
		</citation>
		<descript>
			<langdata>eng</langdata>
			<abstract>World Mountain Peaks, 1996 is a point theme representing mountain peaks worldwide.  Attribute information includes the mountain name, the name of the mountain system, range, or territory where the peak is located, and the elevation of the peak.</abstract>
			<purpose>For educational, non-commercial purposes.  This dataset is appropriate for use in a GIS.</purpose>
			<supplinf>The distribution and elevations of the highest parts of mountains, massifs, and ranges, are two of the most meaningful characteristics for describing and exploring the outer features of the earth's relief. Peaks, together with other relief characteristics such as morphology, genesis, and structure and components of the landscape, provide a better understanding of the present-day nature and economic development of the continents.</supplinf>
		</descript>
		<timeperd>
			<timeinfo>
				<sngdate>
					<caldate>1996</caldate>
				</sngdate>
			</timeinfo>
			<current>publication date</current>
		</timeperd>
		<status>
			<progress>Complete</progress>
			<update>None planned</update>
		</status>
		<spdom>
			<bounding>
				<westbc>
-180</westbc>
					<eastbc>
180</eastbc>
						<northbc>
85</northbc>
							<southbc>
-85</southbc>
							</bounding>
						</spdom>
						<keywords>
							<theme>
								<themekt>ISO 19115 Topic Category</themekt>
								<themekey>geoscientificinformation</themekey>
							</theme>
							<theme>
								<themekt>None</themekt>
								<themekey>Peaks</themekey>
								<themekey>Mountains</themekey>
							</theme>
							<place>
								<placekt>GeoNames</placekt>
								<placekey>Earth (6295630)</placekey>
							</place>
							<place>
								<placekt>Library of Congress Subject Headings</placekt>
								<placekey>Earth</placekey>
							</place>
							<temporal>
								<tempkt>None</tempkt>
								<tempkey>1996</tempkey>
							</temporal>
						</keywords>
						<accconst>For current Columbia affiliates only.</accconst>

						<useconst>For educational, non-commercial use only.</useconst>
						<ptcontac>
							<cntinfo>
								<cntorgp>
									<cntorg>ESRI</cntorg>
									<cntper>Data Team</cntper>
								</cntorgp>
								<cntaddr>
									<addrtype>mailing and physical address</addrtype>
									<address>380 New York Street</address>
									<city>Redlands</city>
									<state>California</state>
									<postal>92373-8100</postal>
									<country>USA</country>
								</cntaddr>
								<cntvoice>909-793-2853</cntvoice>
								<cntfax>909-793-5953</cntfax>
								<cntemail>info@esri.com</cntemail>
								<hours>7:00 a.m.-5:30 p.m. Pacific time, Monday-Friday</hours>
								<cntinst>n the United States- Please direct all inquiries regarding software/data pricing and consulting services to your local ESRI Regional Office. For support, you may contact Technical Support by telephone (voice) between 6:00 a.m. and 5:00 p.m. Pacific time, Monday through Friday, by dialing 888-377-4575; facsimile (fax) available at 909-792-0960; electronic mail (e-mail) support@esri.com; or visit http://support.esri.com; ESRI holidays excluded. Outside the United States Please direct all inquiries regarding software/data pricing, sales, support, and consulting services to your local ESRI International Distributor. This information can be found at http://gis.esri.com/intldist/contactint.cfm. For other questions or comments, you may contact ESRI headquarters by e-mail, telephone, or fax or write to us.</cntinst>
							</cntinfo>
						</ptcontac>
						<browse>
							<browsen>http://www.columbia.edu/acis/eds/gis/pix/cat/peaks.jpg</browsen>
							<browsed>Thumbnail</browsed>
							<browset>JPEG</browset>
						</browse>
						<native>Microsoft Windows XP Version 5.1 (Build 2600) Service Pack 3; ESRI ArcCatalog 9.3.1.1850</native>
					</idinfo>
					<dataqual>
						<lineage>
							<srcinfo>
								<srccite>
									<citeinfo>
										<origin>The USSR Army Headquarters, Military Topographic Department</origin>
										<pubdate>1984</pubdate>
										<title>Atlas ofitsera</title>
										<geoform>atlas</geoform>
										<pubinfo>
											<pubplace>Moscow</pubplace>
											<publish>The USSR Army Headquarters, Military Topographic Department</publish>
										</pubinfo>
									</citeinfo>
								</srccite>
								<typesrc>paper</typesrc>
								<srccitea>Atlas ofitsera</srccitea>
							</srcinfo>
							<srcinfo>
								<srccite>
									<citeinfo>
										<pubdate>1994</pubdate>
										<title>The Atlas of the World, Comprehensive Edition</title>
										<geoform>atlas</geoform>
										<pubinfo>
											<pubplace>London</pubplace>
											<publish>Times Books</publish>
										</pubinfo>
									</citeinfo>
								</srccite>
								<typesrc>paper</typesrc>
								<srccitea>The Atlas of the World, Comprehensive Edition</srccitea>
							</srcinfo>
							<srcinfo>
								<srccite>
									<citeinfo>
										<origin>Treshnikov, A.F.</origin>
										<pubdate>1988</pubdate>
										<title>Geograficheskiy Ehtsiklopedicheskiy Slovar': ponyatiya i terminy</title>
										<geoform>atlas</geoform>
										<pubinfo>
											<pubplace>Moscow</pubplace>
											<publish>Sovetskaya Ehtsiklopedia</publish>
										</pubinfo>
									</citeinfo>
								</srccite>
								<typesrc>paper</typesrc>
								<srccitea>Geograficheskiy Ehtsiklopedicheskiy Slovar': ponyatiya i terminy</srccitea>
							</srcinfo>
							<procstep>
								<procdesc>The database contains information on significant peaks. The data were acquired by cartographic, textual, and reference sources. The coordinates of the peaks were given by reference books and maps. The highest and most significant peaks were selected according to mountain systems and, in some cases, countries.</procdesc>
								<srcused>Atlas ofitsera</srcused>
								<srcused>The Atlas of the World, Comprehensive Edition</srcused>
								<srcused>Geograficheskiy Ehtsiklopedicheskiy Slovar': ponyatiya i terminy</srcused>
								<procdate>Unknown</procdate>
								<proccont>
									<cntinfo>
										<cntaddr>
										</cntaddr>
									</cntinfo>
								</proccont>
							</procstep>
							<procstep>
								<procdesc>Datasets for each continent were converted from ESRI coverage to the ESRI shapefile format using the 'copy features' tool and merged into one layer using the 'merge' tool.</procdesc>
								<procdate>20090507</procdate>
								<proccont>
									<cntinfo>
										<cntperp>
											<cntper>GIS/Map Librarian</cntper>
											<cntorg>Research Data Services (RDS), Columbia University Libraries</cntorg>
										</cntperp>
										<cntaddr>
											<addrtype>mailing and physical address</addrtype>
											<address>420 W. 118th St. 215 IAB, MC 3301</address>
											<city>New York</city>
											<state>NY</state>
											<postal>10027</postal>
											<country>USA</country>
										</cntaddr>
										<cntvoice>(212) 854-6012</cntvoice>
										<cntemail>data@library.columbia.edu</cntemail>
									</cntinfo>
								</proccont>
							</procstep>
						</lineage>
					</dataqual>
					<spdoinfo>
						<direct>Vector</direct>
						<ptvctinf>
							<sdtsterm>
								<sdtstype>Entity point</sdtstype>
								<ptvctcnt>187</ptvctcnt>
							</sdtsterm>
						</ptvctinf>
					</spdoinfo>
					<spref>
						<horizsys>
							<geograph>
								<latres>0.000000</latres>
								<longres>0.000000</longres>
								<geogunit>Decimal degrees</geogunit>
							</geograph>
							<geodetic>
								<horizdn>D_Clarke_1866</horizdn>
								<ellips>Clarke 1866</ellips>
								<semiaxis>6378206.400000</semiaxis>
								<denflat>294.978698</denflat>
							</geodetic>
						</horizsys>
					</spref>
					<eainfo>
						<detailed>
							<enttyp>
								<enttypl>
peaks</enttypl>
									<enttypd>Mountain peaks</enttypd>
								</enttyp>
								<attr>
									<attrlabl>FID</attrlabl>
									<attrdef>Internal feature number.</attrdef>
									<attrdefs>ESRI</attrdefs>
									<attrdomv>
										<udom>Sequential unique whole numbers that are automatically generated.</udom>
									</attrdomv>
								</attr>
								<attr>
									<attrlabl>Shape</attrlabl>
									<attrdef>Feature geometry.</attrdef>
									<attrdefs>ESRI</attrdefs>
									<attrdomv>
										<udom>Coordinates defining the features.</udom>
									</attrdomv>
								</attr>
								<attr>
									<attrlabl>AREA</attrlabl>
									<attrdef>Area</attrdef>
								</attr>
								<attr>
									<attrlabl>PERIMETER</attrlabl>
									<attrdef>Perimeter</attrdef>
								</attr>
								<attr>
									<attrlabl>SAHTDD_</attrlabl>
									<attrdef>South America</attrdef>
								</attr>
								<attr>
									<attrlabl>SAHTDD_ID</attrlabl>
									<attrdef>South America</attrdef>
								</attr>
								<attr>
									<attrlabl>NAME</attrlabl>
									<attrdef>Mountain name.</attrdef>
								</attr>
								<attr>
									<attrlabl>DIAK_CDE</attrlabl>
									<attrdef>Code for any diacritical marks in the mountain name.</attrdef>
								</attr>
								<attr>
									<attrlabl>ELEV</attrlabl>
									<attrdef>The elevation of the mountain in meters above sea level</attrdef>
								</attr>
								<attr>
									<attrlabl>MTN_SYS</attrlabl>
									<attrdef>The name of the mountain system, range, or territory where the peak is locateed</attrdef>
								</attr>
								<attr>
									<attrlabl>FIPS_CNTRY</attrlabl>
									<attrdef>two-letter country code</attrdef>
								</attr>
								<attr>
									<attrlabl>POLYGONID</attrlabl>
									<attrdef>Polygon ID</attrdef>
								</attr>
								<attr>
									<attrlabl>SCALE</attrlabl>
									<attrdef>Scale</attrdef>
								</attr>
								<attr>
									<attrlabl>ANGLE</attrlabl>
									<attrdef>ANgle</attrdef>
								</attr>
								<attr>
									<attrlabl>NAHTDD_</attrlabl>
									<attrdef>North America</attrdef>
								</attr>
								<attr>
									<attrlabl>NAHTDD_ID</attrlabl>
									<attrdef>North America</attrdef>
								</attr>
								<attr>
									<attrlabl>EUHTDD_</attrlabl>
									<attrdef>Europe</attrdef>
								</attr>
								<attr>
									<attrlabl>EUHTDD_ID</attrlabl>
									<attrdef>Europe</attrdef>
								</attr>
								<attr>
									<attrlabl>AUHTDD_</attrlabl>
									<attrdef>Australia</attrdef>
								</attr>
								<attr>
									<attrlabl>AUHTDD_ID</attrlabl>
									<attrdef>Australia</attrdef>
								</attr>
								<attr>
									<attrlabl>ASHTDD_</attrlabl>
									<attrdef>Asia</attrdef>
								</attr>
								<attr>
									<attrlabl>ASHTDD_ID</attrlabl>
									<attrdef>Asia</attrdef>
								</attr>
								<attr>
									<attrlabl>ANHTLB_</attrlabl>
									<attrdef>Antarctica</attrdef>
								</attr>
								<attr>
									<attrlabl>ANHTLB_ID</attrlabl>
									<attrdef>Antarctica</attrdef>
								</attr>
								<attr>
									<attrlabl>AFHTDD_</attrlabl>
									<attrdef>Africa</attrdef>
								</attr>
								<attr>
									<attrlabl>AFHTDD_ID</attrlabl>
									<attrdef>Africa</attrdef>
								</attr>
							</detailed>
						</eainfo>
						<distinfo>
							<distrib>
								<cntinfo>
									<cntorgp>
										<cntorg>ESRI; ESRI International Distributors</cntorg>
									</cntorgp>
									<cntaddr>
										<addrtype>mailing and physical address</addrtype>
										<address>380 New York Street</address>
										<city>Redlands</city>
										<state>California</state>
										<postal>92373-8100</postal>
										<country>USA</country>
									</cntaddr>
									<cntvoice>800-447-9778</cntvoice>
									<cntinst>In the United States, contact the ESRI Telebusiness staff at 800-447-9778 for more information about our software and data. Outside the United States, please direct all inquiries to your local ESRI International Distributor. This information can be found at http://gis.esri.com/intldist/contactint.cfm.</cntinst>
								</cntinfo>
							</distrib>
							<resdesc>esri_1996_world_peaks</resdesc>
							<stdorder>
								<digform>
									<digtinfo>
										<formname>GeoPackage</formname>
										<formspec>zip</formspec>

										<transize>TBD</transize>
									</digtinfo>
								</digform>
							</stdorder>
						</distinfo>
						<metainfo>
							<metd>20090701</metd>
							<metc>
								<cntinfo>
									<cntorgp>
										<cntorg>Research Data Services (RDS), Columbia University Libraries</cntorg>
										<cntper>GIS/Metadata Librarian</cntper>
									</cntorgp>
									<cntaddr>
										<addrtype>mailing and physical address</addrtype>
										<address>420 W. 118th St. 215 IAB, MC 3301</address>
										<city>New York</city>
										<state>NY</state>
										<postal>10027</postal>
										<country>USA</country>
									</cntaddr>
									<cntvoice>(212) 854-6012</cntvoice>
									<cntemail>data@library.columbia.edu</cntemail>
									<hours>7:00 a.m.-5:30 p.m. Pacific time, Monday-Friday</hours>
								</cntinfo>
							</metc>
							<metstdn>FGDC Content Standards for Digital Geospatial Metadata</metstdn>
							<metstdv>FGDC-STD-001-1998</metstdv>
							<mettc>local time</mettc>
						</metainfo>
					</metadata>
