<?xml version="1.0" encoding="UTF-8"?>
<!--<!DOCTYPE metadata SYSTEM "http://www.esri.com/metadata/esriprof80.dtd">-->
<metadata xml:lang="en">
	<idinfo>
		<native>Microsoft Windows Vista Version 6.1 (Build 7600) ; ESRI ArcCatalog 9.3.1.4000</native>
		<descript>
			<langdata>eng</langdata>
			<abstract>United States Airports is a polygon theme representing airport grounds and airport runways within the United States. All airports have a boundary, and most have at least one runway.</abstract>
			<purpose>United States Airports provides the boundaries for thousands of airports and runways. There are many attributes that describe each airport, for example, location ID (airport code), owner, elevation, congestion level, large certified air carrier enplanements, foreign enplanements, hub size, and tower type.</purpose>
			<supplinf>Largest scale when displaying the data: 1:50,000.</supplinf>
		</descript>
		<citation>
			<citeinfo>
				<origin>Tom Tom Global Content B.V. (Firm)</origin>
				<pubdate>2012</pubdate>
				<title>United States Airports, 2012</title>
				<ftname>airportp.sdc</ftname>
				<geoform>vector digital data</geoform>
				<edition>2012</edition>
				<serinfo>
					<sername>Data &amp; Maps for ArcGIS</sername>
					<issue>2012 - World, Europe, and United States</issue>
				</serinfo>
				<pubinfo>
					<pubplace>Redlands, California, USA</pubplace>
					<publish>Environmental Systems Research Institute (Redlands, Calif.)</publish>
				</pubinfo>
				<origin>Environmental Systems Research Institute (Redlands, Calif.)</origin>
				<onlink>https://www1.columbia.edu/sec/acis/eds/dgate/studies/C1301/data/esri_2012_us_airportp.zip</onlink>
			</citeinfo>
		</citation>
		<timeperd>
			<current>publication date</current>
			<timeinfo>
				<mdattim>
					<sngdate>
						<caldate>201109</caldate>
					</sngdate>
					<sngdate>
						<caldate>201003</caldate>
					</sngdate>
					<sngdate>
						<caldate>2002</caldate>
					</sngdate>
					<sngdate>
						<caldate>2003</caldate>
					</sngdate>
					<sngdate>
						<caldate>199402</caldate>
					</sngdate>
					<sngdate>
						<caldate>199405</caldate>
					</sngdate>
					<sngdate>
						<caldate>1992</caldate>
					</sngdate>
					<sngdate>
						<caldate>1991</caldate>
					</sngdate>
				</mdattim>
			</timeinfo>
		</timeperd>
		<status>
			<progress>Complete</progress>
			<update>Annually</update>
		</status>
		<spdom>
			<bounding>
				<westbc>-171.744183</westbc>
				<eastbc>-65.981677</eastbc>
				<northbc>71.289058</northbc>
				<southbc>18.003798</southbc>
			</bounding>
			<lboundng>
				<leftbc>-171.744183</leftbc>
				<rightbc>-65.981677</rightbc>
				<bottombc>18.003798</bottombc>
				<topbc>71.289058</topbc>
			</lboundng>
		</spdom>
		<keywords>
			<theme>
				<themekt>None</themekt>
				<themekey>polygon</themekey>
				<themekey>airports</themekey>
				<themekey>runways</themekey>
				<themekey>enplanements</themekey>
				<themekey>hubs</themekey>
				<themekey>control towers</themekey>
				<themekey>airport codes</themekey>
				<themekey>transportation</themekey>
			</theme>
			<place>
				<placekt>GeoNames</placekt>
				<placekey>United States</placekey>
			</place>
			<place>
				<placekt>Library of Congress Subject Headings</placekt>
				<placekey>Puerto Rico</placekey>
			</place>
			<temporal>
				<tempkey>2011</tempkey>
				<tempkey>2010</tempkey>
				<tempkey>2002</tempkey>
				<tempkey>2003</tempkey>
				<tempkt>None</tempkt>
				<tempkey>1994</tempkey>
				<tempkey>1992</tempkey>
				<tempkey>1991</tempkey>
			</temporal>
			<theme>
				<themekt>ISO 19115 Topic Category</themekt>
				<themekey>Structure</themekey>
			</theme>
		</keywords>
		<accconst>For current Columbia affiliates only.</accconst>

		<useconst>For educational, non-commercial use only.</useconst>
		<natvform>SDC Feature Database</natvform>
		<ptcontac>
			<cntinfo>
				<cntorgp>
					<cntorg>Esri</cntorg>
					<cntper>ArcGIS Content Team</cntper>
				</cntorgp>
				<cntaddr>
					<addrtype>mailing and physical address</addrtype>
					<address>380 New York Street</address>
					<city>Redlands</city>
					<state>California</state>
					<postal>92373-8100</postal>
					<country>USA</country>
				</cntaddr>
				<cntvoice>909-793-2853</cntvoice>
				<cntfax>909-793-5953</cntfax>
				<cntemail>info@esri.com</cntemail>
				<hours>7:00 a.m.-5:30 p.m. Pacific time, Monday-Friday</hours>
				<cntinst>In the United States-
Please direct all inquiries regarding software/data pricing and consulting services to your local Esri Regional Office.  For support, you may contact Esri Support Center by telephone (voice) between 5:00 a.m. and 5:00 p.m. Pacific time, Monday through Friday, by dialing 888-377-4575; facsimile (fax) available at 909-792-0960; electronic mail (e-mail) support@esri.com; or visit http://support.esri.com/; Esri holidays excluded.

Outside the United States-
Please direct all inquiries regarding software/data pricing, sales, support, and consulting services to your local Esri Office.  This information can be found at http://www.esri.com/about-esri/locations.html.

For other questions or comments, you may contact Esri headquarters by e-mail, telephone, or fax or write to us.</cntinst>
			</cntinfo>
		</ptcontac>
		<browse>
			<browsen>http://www.columbia.edu/acis/eds/gis/pix/cat/ESRI_2010_us_airportp.jpg</browsen>
			<browsed>Thumbnail</browsed>
			<browset>jpg</browset>
		</browse>
	</idinfo>
	<dataqual>
		<lineage>
			<srcinfo>
				<srccite>
					<citeinfo>
						<title>TomTom MultiNet POI North America; TomTom MultiNet North America</title>
						<origin>TomTom North America, Inc.</origin>
						<pubdate>201109; 201003</pubdate>
						<edition>Versions 2011.09 and 2010.03</edition>
						<geoform>vector digital data</geoform>
						<serinfo>
							<sername>TomTom MultiNet POI North America; TomTom MultiNet North America</sername>
							<issue>Versions 2011.09 and 2010.03</issue>
						</serinfo>
						<pubinfo>
							<publish>TomTom North America, Inc.</publish>
							<pubplace>Lebanon, New Hampshire, USA</pubplace>
						</pubinfo>
						<onlink>http://www.tomtom.com/</onlink>
					</citeinfo>
				</srccite>
				<typesrc>DVD-ROM</typesrc>
				<srctime>
					<timeinfo>
						<mdattim>
							<sngdate>
								<caldate>201109</caldate>
							</sngdate>
							<sngdate>
								<caldate>201003</caldate>
							</sngdate>
						</mdattim>
					</timeinfo>
					<srccurr>publication date</srccurr>
				</srctime>
				<srccitea>TomTom MultiNet North America v. 2011.09 and v. 2010.03</srccitea>
				<srccontr>Attribute and geospatial data</srccontr>
			</srcinfo>
			<srcinfo>
				<srccite>
					<citeinfo>
						<origin>Bureau of Transportation Statistics, (comp.)</origin>
						<pubdate>2002</pubdate>
						<title>Public Use Airports, 2012</title>
						<edition>2002</edition>
						<geoform>vector digital data</geoform>
						<pubinfo>
							<pubplace>Washington, DC</pubplace>
							<publish>Bureau of Transportation Statistics</publish>
						</pubinfo>
						<othercit>From the National Transportation Atlas Databases (NTAD) 2002 CD-ROM.</othercit>
						<onlink>http://www.bts.gov/gis/</onlink>
					</citeinfo>
				</srccite>
				<typesrc>CD-ROM</typesrc>
				<srctime>
					<timeinfo>
						<sngdate>
							<caldate>2002</caldate>
						</sngdate>
					</timeinfo>
					<srccurr>publication date</srccurr>
				</srctime>
				<srccitea>NTAD 2002 - Airports</srccitea>
				<srccontr>Attribute data</srccontr>
			</srcinfo>
			<srcinfo>
				<typesrc>online</typesrc>
				<srccitea>AirNav, LLC</srccitea>
				<srccontr>Attribute data</srccontr>
				<srccite>
					<citeinfo>
						<origin>AirNav, LLC</origin>
						<title>Airport Information</title>
						<geoform>tabular digital data</geoform>
						<pubinfo>
							<pubplace>online</pubplace>
							<publish>AirNav, LLC</publish>
						</pubinfo>
						<othercit>Accessed website in 2003.</othercit>
						<onlink>http://www.airnav.com/</onlink>
					</citeinfo>
				</srccite>
				<srctime>
					<timeinfo>
						<sngdate>
							<caldate>2003</caldate>
						</sngdate>
					</timeinfo>
					<srccurr>publication date</srccurr>
				</srctime>
			</srcinfo>
			<procstep>
				<srcused>TomTom MultiNet North America v. 2011.09 and v. 2010.03</srcused>
				<srcused>NTAD 2002 - Airports</srcused>
				<srcused>AirNav, LLC</srcused>
				<procdesc>The following steps were performed by Esri: Extracted the Points of Interest (POI) data set from TomTom MultiNet POI North America v. 2011.09. Selected features that intersected Data &amp; Maps 10 U.S. Counties to get the U.S. features only. Selected the airport ground and runway features. Removed all fields except FEATTYP, NAME, and ACRON. Renamed MultiNet field FEATTYP to MNFC. Renamed MultiNet field ACRON to LOC_ID. Added field FCC and calculated its values based on MultiNet FEATTYP equivalents. Added field FEATTYPE and copied its values from MultiNet FEATTYP descriptions. Attached and formatted the fields from Data &amp; Maps 10 U.S. Airports (source dates - 1991, 1992, and 1994). Put a "-999" value into all records that did not find a match for the field ELEVATION. Put a "0" value into all records that did not find a match for the fields LRGCERTENP, COMM_ENP, AIRTAXIENP, FOREIGNENP and INTRANENP. Converted the data set to SDC. Created ArcGIS layer file (.lyr), projection file (.prj), and spatial indices.</procdesc>
				<procsv>ArcGIS 10, ArcGIS 9</procsv>
				<procdate>20111221</procdate>
			</procstep>
		</lineage>
		<posacc>
			<horizpa>
				<horizpar>Horizontal positional accuracy is dependent on geographic area. In most areas, accuracy is between 5 and 25 meters (16 and 82 feet). In some areas, accuracy is off by up to several tens of meters (100 feet or more). In the poorest areas, accuracy is off by up to 100 meters (328 feet).</horizpar>
			</horizpa>
		</posacc>
		<logic>The shapefile is converted to SDC (Smart Data Compression) format using tools in ArcGIS.  The SDC data set is then imported into a file geodatabase to verify, validate, and if needed repair the geometry.</logic>
		<complete>After processing, the data set is checked for drawing display and number of records and file sizes compared with source materials.</complete>
	</dataqual>
	<spdoinfo>
		<direct>Vector</direct>
		<ptvctinf>
			<esriterm Name="airportp">
				<efeatyp>Simple</efeatyp>
				<efeageom>Polygon</efeageom>
				<esritopo>FALSE</esritopo>
				<efeacnt>6444</efeacnt>
				<spindex>TRUE</spindex>
				<linrefer>FALSE</linrefer>
				<featdesc>U.S. Airport</featdesc>
			</esriterm>
			<sdtsterm Name="airportp">
				<sdtstype>G-polygon</sdtstype>
				<ptvctcnt>6444</ptvctcnt>
			</sdtsterm>
		</ptvctinf>
	</spdoinfo>
	<spref>
		<horizsys>
			<cordsysn>
				<geogcsn>GCS_WGS_1984</geogcsn>
			</cordsysn>
			<geograph>
				<geogunit>Decimal degrees</geogunit>
				<latres>0.000000</latres>
				<longres>0.000000</longres>
			</geograph>
			<geodetic>
				<horizdn>D_WGS_1984</horizdn>
				<ellips>WGS_1984</ellips>
				<semiaxis>6378137.000000</semiaxis>
				<denflat>298.257224</denflat>
			</geodetic>
		</horizsys>
	</spref>
	<eainfo>
		<detailed Name="airportp">
			<enttyp>
				<enttypl>airportp</enttypl>
				<enttypt>Feature Class</enttypt>
				<enttypc>6444</enttypc>
				<enttypd>The polygons represent the airport grounds and airport runways within the United States.</enttypd>
				<enttypds>TomTom North America, Inc.</enttypds>
			</enttyp>
			<attr>
				<attrlabl>ObjectID</attrlabl>
				<attalias>ObjectID</attalias>
				<attrtype>OID</attrtype>
				<attwidth>4</attwidth>
				<atprecis>0</atprecis>
				<attscale>0</attscale>
				<attrdef>Internal feature number.</attrdef>
				<attrdefs>Esri</attrdefs>
				<attrdomv>
					<udom>Sequential unique whole numbers that are automatically generated.</udom>
				</attrdomv>
			</attr>
			<attr>
				<attrlabl>Shape</attrlabl>
				<attalias>Shape</attalias>
				<attrtype>Geometry</attrtype>
				<attwidth>0</attwidth>
				<atprecis>0</atprecis>
				<attscale>0</attscale>
				<attrdef>Feature geometry.</attrdef>
				<attrdefs>Esri</attrdefs>
				<attrdomv>
					<udom>Coordinates defining the features.</udom>
				</attrdomv>
			</attr>
			<attr>
				<attrlabl>NAME</attrlabl>
				<attalias>NAME</attalias>
				<attrtype>String</attrtype>
				<attwidth>150</attwidth>
				<attrdef>The official name of the airport.</attrdef>
				<attrdefs>TomTom North America, Inc.</attrdefs>
				<attrdomv>
					<udom>Names for the features.</udom>
				</attrdomv>
				<atprecis>0</atprecis>
				<attscale>0</attscale>
			</attr>
			<attr>
				<attrlabl>FCC</attrlabl>
				<attalias>FCC</attalias>
				<attrtype>String</attrtype>
				<attwidth>254</attwidth>
				<attrdef>The Feature Classification Code of the airport/runway.</attrdef>
				<attrdomv>
					<codesetd>
						<codesetn>Census Feature Classification Codes (also called "FCC")</codesetn>
						<codesets>Department of Commerce, Census Bureau</codesets>
					</codesetd>
				</attrdomv>
				<attrdefs>Department of Commerce, Census Bureau</attrdefs>
				<atprecis>0</atprecis>
				<attscale>0</attscale>
			</attr>
			<attr>
				<attrlabl>FEATTYPE</attrlabl>
				<attalias>FEATTYPE</attalias>
				<attrtype>String</attrtype>
				<attwidth>40</attwidth>
				<atprecis>0</atprecis>
				<attscale>0</attscale>
				<attrdef>The feature type description of the airport/runway.</attrdef>
				<attrdefs>TomTom North America, Inc.</attrdefs>
				<attrdomv>
					<codesetd>
						<codesetn>MultiNet Feature Code Descriptions</codesetn>
						<codesets>TomTom North America, Inc.</codesets>
					</codesetd>
				</attrdomv>
			</attr>
			<attr>
				<attrlabl>MNFC</attrlabl>
				<attalias>MNFC</attalias>
				<attrtype>Integer</attrtype>
				<attwidth>4</attwidth>
				<atprecis>5</atprecis>
				<attscale>0</attscale>
				<attrdef>The MultiNet feature code of the airport/runway.</attrdef>
				<attrdefs>TomTom North America, Inc.</attrdefs>
				<attrdomv>
					<codesetd>
						<codesetn>MultiNet Feature Codes</codesetn>
						<codesets>TomTom North America, Inc.</codesets>
					</codesetd>
				</attrdomv>
			</attr>
			<attr>
				<attrlabl>LOC_ID</attrlabl>
				<attalias>LOC_ID</attalias>
				<attrtype>String</attrtype>
				<attwidth>20</attwidth>
				<attrdef>The three- or four-character international identifier code of the airport/runway.</attrdef>
				<attrdefs>International Air Transport Association (IATA)</attrdefs>
				<attrdomv>
					<codesetd>
						<codesetn>Airport Codes</codesetn>
						<codesets>International Air Transport Association (IATA)</codesets>
					</codesetd>
				</attrdomv>
				<atprecis>0</atprecis>
				<attscale>0</attscale>
			</attr>
			<attr>
				<attrlabl>USE</attrlabl>
				<attalias>USE</attalias>
				<attrtype>String</attrtype>
				<attwidth>2</attwidth>
				<attrdomv>
					<edom>
						<edomvds>National Flight Data Center (NFDC)</edomvds>
						<edomv>PU</edomv>
						<edomvd>Public use.</edomvd>
					</edom>
					<edom>
						<edomvds>National Flight Data Center (NFDC)</edomvds>
						<edomv>PR</edomv>
						<edomvd>Private use.</edomvd>
					</edom>
				</attrdomv>
				<attrdef>The identification of the use of the airport/runway.</attrdef>
				<attrdefs>National Flight Data Center (NFDC)</attrdefs>
				<atprecis>0</atprecis>
				<attscale>0</attscale>
			</attr>
			<attr>
				<attrlabl>OWNERNAME</attrlabl>
				<attalias>OWNERNAME</attalias>
				<attrtype>String</attrtype>
				<attwidth>30</attwidth>
				<attrdef>The owner name of the airport/runway.</attrdef>
				<attrdefs>National Flight Data Center (NFDC)</attrdefs>
				<attrdomv>
					<udom>Names for the features.</udom>
				</attrdomv>
				<atprecis>0</atprecis>
				<attscale>0</attscale>
			</attr>
			<attr>
				<attrlabl>ELEVATION</attrlabl>
				<attalias>ELEVATION</attalias>
				<attrtype>Integer</attrtype>
				<attwidth>4</attwidth>
				<attrdef>The elevation in feet above sea level of the airport/runway.</attrdef>
				<attrdefs>National Flight Data Center (NFDC)</attrdefs>
				<attrdomv>
					<udom>Numbers for the features.</udom>
				</attrdomv>
				<atprecis>9</atprecis>
				<attscale>0</attscale>
				<attrdomv>
					<edom>
						<edomv>-999</edomv>
						<edomvd>Unknown.</edomvd>
						<edomvds>Esri</edomvds>
					</edom>
				</attrdomv>
			</attr>
			<attr>
				<attrlabl>CONGES_LEV</attrlabl>
				<attalias>CONGES_LEV</attalias>
				<attrtype>String</attrtype>
				<attwidth>1</attwidth>
				<attrdomv>
					<edom>
						<edomvds>National Plan of Integrated Airport Systems (NPIAS)</edomvds>
						<edomv>S</edomv>
						<edomvd>Severe.</edomvd>
					</edom>
					<edom>
						<edomvds>National Plan of Integrated Airport Systems (NPIAS)</edomvds>
						<edomv>M</edomv>
						<edomvd>Moderate.</edomvd>
					</edom>
					<edom>
						<edomvds>National Plan of Integrated Airport Systems (NPIAS)</edomvds>
						<edomv>U</edomv>
						<edomvd>Uncongested.</edomvd>
					</edom>
					<edom>
						<edomvds>National Plan of Integrated Airport Systems (NPIAS)</edomvds>
						<edomv>O</edomv>
						<edomvd>Entry missing.</edomvd>
					</edom>
					<edom>
						<edomv>blank</edomv>
						<edomvd>Unknown.</edomvd>
						<edomvds>Esri</edomvds>
					</edom>
				</attrdomv>
				<attrdef>The congestion level of the airport.</attrdef>
				<attrdefs>National Plan of Integrated Airport Systems (NPIAS)</attrdefs>
				<atprecis>0</atprecis>
				<attscale>0</attscale>
			</attr>
			<attr>
				<attrlabl>SERV_LEV</attrlabl>
				<attalias>SERV_LEV</attalias>
				<attrtype>String</attrtype>
				<attwidth>2</attwidth>
				<attrdef>The service level of the airport.</attrdef>
				<attrdomv>
					<edom>
						<edomvds>National Plan of Integrated Airport Systems (NPIAS)</edomvds>
						<edomv>PR</edomv>
						<edomvd>Primary commercial service airport.</edomvd>
					</edom>
					<edom>
						<edomvds>National Plan of Integrated Airport Systems (NPIAS)</edomvds>
						<edomv>CM</edomv>
						<edomvd>Commercial service other than primary airport.</edomvd>
					</edom>
					<edom>
						<edomvds>National Plan of Integrated Airport Systems (NPIAS)</edomvds>
						<edomv>CR</edomv>
						<edomvd>Commercial service airport that also serves as a reliever airport.</edomvd>
					</edom>
					<edom>
						<edomvds>National Plan of Integrated Airport Systems (NPIAS)</edomvds>
						<edomv>GA</edomv>
						<edomvd>General aviation airport.</edomvd>
					</edom>
					<edom>
						<edomvds>National Plan of Integrated Airport Systems (NPIAS)</edomvds>
						<edomv>RL</edomv>
						<edomvd>General aviation airport that serves as a reliever airport or heliport.</edomvd>
					</edom>
					<edom>
						<edomvds>National Plan of Integrated Airport Systems (NPIAS)</edomvds>
						<edomv>GP</edomv>
						<edomvd>General aviation airport that meets the criteria for a primary airport (PR), but has been declared ineligible to be a primary airport.</edomvd>
					</edom>
					<edom>
						<edomvds>National Plan of Integrated Airport Systems (NPIAS)</edomvds>
						<edomv>GC</edomv>
						<edomvd>General aviation airport that meets the criteria for a commercial service other than a primary airport (CM), but has been declared ineligible to be a commercial airport.</edomvd>
					</edom>
					<edom>
						<edomvds>Esri</edomvds>
						<edomv>blank</edomv>
						<edomvd>Unknown.</edomvd>
					</edom>
				</attrdomv>
				<attrdefs>National Plan of Integrated Airport Systems (NPIAS)</attrdefs>
				<atprecis>0</atprecis>
				<attscale>0</attscale>
			</attr>
			<attr>
				<attrlabl>LRGCERTENP</attrlabl>
				<attalias>LRGCERTENP</attalias>
				<attrtype>Integer</attrtype>
				<attwidth>4</attwidth>
				<attrdef>The total domestic and foreign enplanements on large certificated U.S. air carriers during calendar year 1992.</attrdef>
				<attrdefs>TomTom North America, Inc.</attrdefs>
				<attrdomv>
					<udom>Numbers for the features.</udom>
				</attrdomv>
				<atprecis>9</atprecis>
				<attscale>0</attscale>
			</attr>
			<attr>
				<attrlabl>COMM_ENP</attrlabl>
				<attalias>COMM_ENP</attalias>
				<attrtype>Integer</attrtype>
				<attwidth>4</attwidth>
				<attrdefs>TomTom North America, Inc.</attrdefs>
				<attrdef>The total enplanements by small certificated air carriers during calendar year 1992 operating scheduled service.</attrdef>
				<attrdomv>
					<udom>Numbers for the features.</udom>
				</attrdomv>
				<atprecis>9</atprecis>
				<attscale>0</attscale>
			</attr>
			<attr>
				<attrlabl>AIRTAXIENP</attrlabl>
				<attalias>AIRTAXIENP</attalias>
				<attrtype>Integer</attrtype>
				<attwidth>4</attwidth>
				<attrdefs>TomTom North America, Inc.</attrdefs>
				<attrdef>The total enplanements on air taxis during calendar year 1992.</attrdef>
				<attrdomv>
					<udom>Numbers for the features.</udom>
				</attrdomv>
				<atprecis>9</atprecis>
				<attscale>0</attscale>
			</attr>
			<attr>
				<attrlabl>FOREIGNENP</attrlabl>
				<attalias>FOREIGNENP</attalias>
				<attrtype>Integer</attrtype>
				<attwidth>4</attwidth>
				<attrdefs>TomTom North America, Inc.</attrdefs>
				<attrdef>The total enplanements by foreign carriers during calendar year 1992.</attrdef>
				<attrdomv>
					<udom>Numbers for the features.</udom>
				</attrdomv>
				<atprecis>9</atprecis>
				<attscale>0</attscale>
			</attr>
			<attr>
				<attrlabl>INTRANENP</attrlabl>
				<attalias>INTRANENP</attalias>
				<attrtype>Integer</attrtype>
				<attwidth>4</attwidth>
				<attrdefs>TomTom North America, Inc.</attrdefs>
				<attrdef>The 1992 total passengers onboard international flights that transit the airport for purposes other than boarding and de-boarding passengers.</attrdef>
				<attrdomv>
					<udom>Numbers for the features.</udom>
				</attrdomv>
				<atprecis>9</atprecis>
				<attscale>0</attscale>
			</attr>
			<attr>
				<attrlabl>HUB_SIZE</attrlabl>
				<attalias>HUB_SIZE</attalias>
				<attrtype>String</attrtype>
				<attwidth>1</attwidth>
				<attrdefs>Air Carrier Activity Information System (ACAIS)</attrdefs>
				<attrdomv>
					<edom>
						<edomv>L</edomv>
						<edomvd>Large.</edomvd>
						<edomvds>Air Carrier Activity Information System (ACAIS)</edomvds>
					</edom>
					<edom>
						<edomvds>Air Carrier Activity Information System (ACAIS)</edomvds>
						<edomv>M</edomv>
						<edomvd>Medium.</edomvd>
					</edom>
					<edom>
						<edomvds>Air Carrier Activity Information System (ACAIS)</edomvds>
						<edomv>S</edomv>
						<edomvd>Small.</edomvd>
					</edom>
					<edom>
						<edomvds>Air Carrier Activity Information System (ACAIS)</edomvds>
						<edomv>N</edomv>
						<edomvd>Non-hub.</edomvd>
					</edom>
					<edom>
						<edomvds>Air Carrier Activity Information System (ACAIS)</edomvds>
						<edomv>G</edomv>
						<edomvd>General aviation.</edomvd>
					</edom>
				</attrdomv>
				<attrdef>The hub size of the airport based on percent of national enplanements.</attrdef>
				<atprecis>0</atprecis>
				<attscale>0</attscale>
			</attr>
			<attr>
				<attrlabl>TOWER_TYPE</attrlabl>
				<attalias>TOWER_TYPE</attalias>
				<attrtype>String</attrtype>
				<attwidth>1</attwidth>
				<attrdefs>Esri</attrdefs>
				<attrdomv>
					<edom>
						<edomvds>TomTom North America, Inc.</edomvds>
						<edomv>0</edomv>
						<edomvd>No tower.</edomvd>
					</edom>
					<edom>
						<edomvds>TomTom North America, Inc.</edomvds>
						<edomv>1</edomv>
						<edomvd>Terminal Radar Approach Control Facility (TRACON), Radar Approach Control Facility (RAPCON), Combined Center and Radar Approach Control Facility (CERAP).</edomvd>
					</edom>
					<edom>
						<edomvds>TomTom North America, Inc.</edomvds>
						<edomv>2</edomv>
						<edomvd>Radar tower.</edomvd>
					</edom>
					<edom>
						<edomvds>TomTom North America, Inc.</edomvds>
						<edomv>3</edomv>
						<edomvd>Limited radar tower.</edomvd>
					</edom>
					<edom>
						<edomvds>TomTom North America, Inc.</edomvds>
						<edomv>4</edomv>
						<edomvd>Non-radar tower.</edomvd>
					</edom>
					<edom>
						<edomvds>TomTom North America, Inc.</edomvds>
						<edomv>5</edomv>
						<edomvd>Visual Flight Rule (VFR) tower.</edomvd>
					</edom>
					<edom>
						<edomvds>TomTom North America, Inc.</edomvds>
						<edomv>6</edomv>
						<edomvd>Non-Federal Aviation Administration (FAA) facility.</edomvd>
					</edom>
					<edom>
						<edomvds>TomTom North America, Inc.</edomvds>
						<edomv>7</edomv>
						<edomvd>Contract tower.</edomvd>
					</edom>
					<edom>
						<edomv>blank</edomv>
						<edomvd>Unknown.</edomvd>
						<edomvds>Esri</edomvds>
					</edom>
				</attrdomv>
				<attrdef>The tower type code of the airport.</attrdef>
				<atprecis>0</atprecis>
				<attscale>0</attscale>
			</attr>
		</detailed>
	</eainfo>
	<distinfo>
		<stdorder>
			<digform>
				<digtinfo>
					<transize>4.0 MB</transize>
					<dssize>1.708</dssize>
					<formname>GeoPackage</formname>
					
					
				</digtinfo>
				<digtopt>
					<offoptn>
						<offmedia>DVD-ROM</offmedia>
						<reccap>
							<recden>4.38 or 7.95</recden>
							<recdenu>GB (gigabytes)</recdenu>
						</reccap>
						<recfmt>UDF (Universal Disc Format)</recfmt>
					</offoptn>
					<onlinopt>
						<computer>
							<networka>
								<networkr>http://www.ArcGIS.com</networkr>
							</networka>
						</computer>
					</onlinopt>
				</digtopt>
			</digform>
			<fees>Software purchase price</fees>
			<ordering>Data &amp; Maps is available only as part of Esri software.</ordering>
		</stdorder>
		<distrib>
			<cntinfo>
				<cntorgp>
					<cntorg>Environmental Systems Research Institute (Redlands, Calif.)</cntorg>
				</cntorgp>
				<cntinst>In the United States, contact the Esri Telebusiness staff at 800-447-9778 for more information about our software and data.

Outside the United States, please direct all inquiries to your local Esri Office.  This information can be found at http://www.esri.com/about-esri/locations.html.</cntinst>
				<cntaddr>
					<addrtype>mailing and physical address</addrtype>
					<address>380 New York Street</address>
					<city>Redlands</city>
					<state>California</state>
					<postal>92373-8100</postal>
					<country>USA</country>
				</cntaddr>
				<cntvoice>800-447-9778</cntvoice>
			</cntinfo>
		</distrib>
		<techpreq>To use this data requires software that supports SDC files.</techpreq>
		<distliab>See use constraints.</distliab>
		<resdesc>esri_2012_us_airportp</resdesc>
	</distinfo>
	<metainfo>
		<metstdn>FGDC Content Standards for Digital Geospatial Metadata</metstdn>
		<metstdv>FGDC-STD-001-1998</metstdv>
		<mettc>local time</mettc>
		<metd>20130205</metd>
		<metc>
			<cntinfo>
				<cntorgp>
					<cntorg>Research Data Services (RDS), Columbia University Libraries</cntorg>
					<cntper>GIS/Metadata Librarian</cntper>
				</cntorgp>
				<cntaddr>
					<addrtype>mailing and physical address</addrtype>
					<address>420 W. 118th St. 215 IAB, MC 3301</address>
					<city>New York</city>
					<state>NY</state>
					<postal>10027</postal>
				</cntaddr>
				<cntvoice>(212) 854-6012</cntvoice>
				<cntemail>data@library.columbia.edu</cntemail>
			</cntinfo>
		</metc>
	</metainfo>
</metadata>
